{
  "$comment": "This file is autogenerated, do not edit manually, see https://github.com/SAP/abap-file-formats for more information.",
  "$schema": "https://json-schema.org/draft/2020-12/schema",
  "$id": "https://github.com/SAP/abap-file-formats/blob/main/file-formats/uipg/uipg-v1.json",
  "title": "Fiori Launchpad Page Template",
  "description": "Fiori launchpad page template",
  "type": "object",
  "properties": {
    "formatVersion": {
      "title": "Format Version",
      "description": "Format version",
      "type": "string",
      "const": "1"
    },
    "header": {
      "title": "Header",
      "description": "Header",
      "type": "object",
      "properties": {
        "description": {
          "title": "Description",
          "description": "Description of the ABAP object",
          "type": "string",
          "maxLength": 100
        },
        "originalLanguage": {
          "title": "Original Language",
          "description": "Original language of the ABAP object",
          "type": "string",
          "minLength": 2,
          "maxLength": 2,
          "pattern": "^[a-z]+$"
        },
        "abapLanguageVersion": {
          "title": "ABAP Language Version",
          "description": "ABAP language version",
          "type": "string",
          "enum": [
            "standard",
            "cloudDevelopment"
          ],
          "enumTitles": [
            "Standard",
            "ABAP Cloud Development"
          ],
          "enumDescriptions": [
            "Standard",
            "ABAP cloud development"
          ],
          "default": "standard"
        }
      },
      "additionalProperties": false,
      "required": [
        "description",
        "originalLanguage"
      ]
    },
    "generalInformation": {
      "title": "General Information",
      "description": "General information",
      "type": "object",
      "properties": {
        "title": {
          "title": "Title",
          "description": "Title visible to the enduser",
          "type": "string",
          "maxLength": 100
        },
        "description": {
          "title": "Description",
          "description": "Description for design-time tools",
          "type": "string",
          "maxLength": 100
        },
        "mergeId": {
          "title": "Merge ID",
          "description": "Merge ID for merging during run-time",
          "type": "string",
          "maxLength": 35
        }
      },
      "additionalProperties": false,
      "required": [
        "title",
        "description"
      ]
    },
    "sections": {
      "title": "Sections",
      "description": "sections",
      "type": "array",
      "items": {
        "title": "Section",
        "description": "section",
        "type": "object",
        "properties": {
          "id": {
            "title": "ID",
            "description": "Section ID",
            "type": "string",
            "maxLength": 35
          },
          "title": {
            "title": "Title",
            "description": "Section title",
            "type": "string",
            "maxLength": 100
          },
          "items": {
            "title": "Items",
            "description": "Section items",
            "type": "array",
            "items": {
              "title": "Section Item Assignment",
              "description": "section item assignment",
              "type": "object",
              "properties": {
                "id": {
                  "title": "ID",
                  "description": "Item ID",
                  "type": "string",
                  "maxLength": 35
                },
                "type": {
                  "title": "Type",
                  "description": "Item assignment type",
                  "type": "string",
                  "enum": [
                    "tile"
                  ],
                  "enumTitles": [
                    "Tile Assignment"
                  ],
                  "enumDescriptions": [
                    "Tile assignment"
                  ],
                  "default": "tile"
                },
                "tileAssignment": {
                  "title": "Tile Assignment Properties",
                  "description": "tile assignment properties",
                  "type": "object",
                  "properties": {
                    "tileDisplayFormat": {
                      "title": "Tile Display Format",
                      "description": "Describes how the tile is rendered during run-time",
                      "type": "string",
                      "enum": [
                        "standard",
                        "wide",
                        "flat",
                        "flatWide",
                        "link"
                      ],
                      "enumTitles": [
                        "Standard Tile",
                        "Wide Tile",
                        "Flat Tile",
                        "Flat Wide Tile",
                        "Link"
                      ],
                      "enumDescriptions": [
                        "Standard tile",
                        "Wide tile",
                        "Flat tile",
                        "Flat wide tile",
                        "Link"
                      ],
                      "default": "standard"
                    },
                    "tile": {
                      "title": "Tile Reference",
                      "description": "Tile reference",
                      "type": "object",
                      "properties": {
                        "catalogId": {
                          "title": "Catalog ID",
                          "description": "Catalog ID",
                          "type": "string",
                          "maxLength": 35
                        },
                        "catalogType": {
                          "title": "Catalog Type",
                          "description": "Catalog type",
                          "type": "string",
                          "maxLength": 3,
                          "default": "CAT"
                        },
                        "id": {
                          "title": "Item ID",
                          "description": "Item ID",
                          "type": "string",
                          "maxLength": 50
                        }
                      },
                      "additionalProperties": false,
                      "required": [
                        "catalogId",
                        "id"
                      ]
                    },
                    "targetMapping": {
                      "title": "Target Mapping Reference",
                      "description": "Target mapping reference",
                      "type": "object",
                      "properties": {
                        "catalogId": {
                          "title": "Catalog ID",
                          "description": "Catalog ID",
                          "type": "string",
                          "maxLength": 35
                        },
                        "catalogType": {
                          "title": "Catalog Type",
                          "description": "Catalog type",
                          "type": "string",
                          "maxLength": 3,
                          "default": "CAT"
                        },
                        "id": {
                          "title": "Item ID",
                          "description": "Item ID",
                          "type": "string",
                          "maxLength": 50
                        }
                      },
                      "additionalProperties": false,
                      "required": [
                        "catalogId",
                        "id"
                      ]
                    }
                  },
                  "additionalProperties": false,
                  "required": [
                    "tile"
                  ]
                }
              },
              "additionalProperties": false,
              "required": [
                "id"
              ]
            }
          }
        },
        "additionalProperties": false,
        "required": [
          "id"
        ]
      }
    }
  },
  "additionalProperties": false,
  "required": [
    "formatVersion",
    "header",
    "generalInformation"
  ]
}
