{
  "formatVersion": "1",
  "header": {
    "description": "Example ENHO for ABAP file formats",
    "originalLanguage": "en"
  },
  "generalInformation": {
    "enhancementSpot": "Z_AFF_EXAMPLE_ENHS"
  },
  "badiImplementations": [
    {
      "name": "Z_AFF_EXAMPLE_BADI_IMPL",
      "description": "This is an example Badi Implementation",
      "badiDefinition": "Z_AFF_EXAMPLE_BADI_DEFINITION",
      "implementingClass": "Z_AFF_EXAMPLE_BADI_IMPL",
      "isDefaultImplementation": true,
      "isActiveImplementation": true,
      "customizing": "notSupported",
      "filterValues": {
        "or": [
          {
            "and": [
              {
                "filter": {
                  "filtername": "EXAMPLE_FILTER",
                  "filtertype": "string",
                  "comparator": ">",
                  "value": "1"
                }
              },
              {
                "filter": {
                  "filtername": "EXAMPLE_FILTER",
                  "filtertype": "string",
                  "comparator": "<",
                  "value": "5"
                }
              }
            ]
          }
        ]
      }
    }
  ],
  "referencedObjects": [
    {
      "objectType": "CLAS",
      "objectName": "Z_AFF_EXAMPLE_BADI_IMPL",
      "programId": "R3TR",
      "elementUsage": "usedObject",
      "mainObjectType": "CLAS",
      "mainObjectName": "Z_AFF_EXAMPLE_BADI_IMPL"
    },
    {
      "objectType": "ENHS",
      "objectName": "Z_AFF_EXAMPLE_ENHS",
      "programId": "R3TR",
      "elementUsage": "enhancedObject",
      "mainObjectType": "ENHS",
      "mainObjectName": "Z_AFF_EXAMPLE_ENHS"
    },
    {
      "objectType": "INTF",
      "objectName": "Z_AFF_EXAMPLE_BADI_INTF",
      "programId": "R3TR",
      "elementUsage": "usedObject",
      "mainObjectType": "INTF",
      "mainObjectName": "Z_AFF_EXAMPLE_BADI_INTF"
    }
  ]
}
